backend/__init__.py
backend/bounding_polygons.py
backend/config.py
backend/constants.py
backend/geo_utils.py
backend/hydrograph.py
backend/logger.py
backend/persister.py
backend/record.py
backend/source.py
backend/transformer.py
backend/unifier.py
backend/worker.py
backend/connectors/__init__.py
backend/connectors/mappings.py
backend/connectors/st_connector.py
backend/connectors/bor/__init__.py
backend/connectors/bor/source.py
backend/connectors/bor/transformer.py
backend/connectors/ckan/__init__.py
backend/connectors/ckan/source.py
backend/connectors/ckan/transformer.py
backend/connectors/isc_seven_rivers/__init__.py
backend/connectors/isc_seven_rivers/source.py
backend/connectors/isc_seven_rivers/transformer.py
backend/connectors/nmbgmr/__init__.py
backend/connectors/nmbgmr/source.py
backend/connectors/nmbgmr/transformer.py
backend/connectors/nmenv/__init__.py
backend/connectors/nmenv/source.py
backend/connectors/nmenv/transformer.py
backend/connectors/nmose/__init__.py
backend/connectors/nmose/source.py
backend/connectors/nmose/transformer.py
backend/connectors/st2/__init__.py
backend/connectors/st2/source.py
backend/connectors/st2/transformer.py
backend/connectors/usgs/__init__.py
backend/connectors/usgs/source.py
backend/connectors/usgs/transformer.py
backend/connectors/wqp/__init__.py
backend/connectors/wqp/source.py
backend/connectors/wqp/transformer.py
backend/persisters/__init__.py
backend/persisters/geoserver.py
frontend/__init__.py
frontend/cli.py
nmuwd-0.9.10.dist-info/licenses/LICENSE
nmuwd-0.9.10.dist-info/METADATA
nmuwd-0.9.10.dist-info/WHEEL
nmuwd-0.9.10.dist-info/entry_points.txt
nmuwd-0.9.10.dist-info/top_level.txt
nmuwd-0.9.10.dist-info/RECORD
