Metadata-Version: 2.4
Name: nmuwd
Version: 0.9.10
Summary: New Mexico Water Data Integration Engine
Home-page: https://github.com/DataIntegrationGroup/DataIntegrationEngine
Author: Jake Ross
Classifier: Programming Language :: Python :: 3
Classifier: Operating System :: OS Independent
Requires-Python: >=3.6
License-File: LICENSE
Requires-Dist: click==8.2.1
Requires-Dist: flask
Requires-Dist: frost_sta_client
Requires-Dist: Geoalchemy2
Requires-Dist: geopandas
Requires-Dist: google-cloud-storage
Requires-Dist: gunicorn
Requires-Dist: httpx
Requires-Dist: mypy
Requires-Dist: pandas
Requires-Dist: psycopg2-binary
Requires-Dist: pytest
Requires-Dist: pyyaml
Requires-Dist: types-pyyaml
Requires-Dist: urllib3<3.0.0,>=2.2.0
Dynamic: author
Dynamic: classifier
Dynamic: description
Dynamic: description-content-type
Dynamic: home-page
Dynamic: license-file
Dynamic: requires-dist
Dynamic: requires-python
Dynamic: summary
